LICENSE.txt
README.md
setup.py
zhtelecode.py
zhtelecode.egg-info/PKG-INFO
zhtelecode.egg-info/SOURCES.txt
zhtelecode.egg-info/dependency_links.txt
zhtelecode.egg-info/top_level.txt