Metadata-Version: 2.1
Name: zhtelecode
Version: 0.1.0
Summary: Convert between Chinese Telegraph Codes and Unicode Chinese characters.
Home-page: https://github.com/charlessimpson/zhtelecode/
Author: Charles Simpson
License: MIT License
Platform: any
Classifier: Development Status :: 4 - Beta
Classifier: Environment :: Console
Classifier: Intended Audience :: Developers
Classifier: License :: OSI Approved :: MIT License
Classifier: Operating System :: OS Independent
Classifier: Programming Language :: Python :: 3
Classifier: Topic :: Software Development :: Libraries :: Python Modules
Requires-Python: >=3.6
License-File: LICENSE.txt
